{
  "authorDailyContributionsMap": {
    "Johnson-Yee": [
      {
        "date": "2020-10-02",
        "commitResults": [
          {
            "hash": "f6643d47b25d29d268876e6af7a8659dc0b94ca3",
            "messageTitle": "Addition of about us - Johnson",
            "messageBody": "",
            "fileTypesAndContributionMap": {
              "docs": {
                "insertions": 1,
                "deletions": 1
              }
            }
          }
        ]
      }
    ],
    "Lezn0": [
      {
        "date": "2020-10-02",
        "commitResults": [
          {
            "hash": "e25125d6c478ca44531c87b6a1321d72ed0661bd",
            "messageTitle": "Modify AboutUs.md",
            "messageBody": "",
            "fileTypesAndContributionMap": {
              "docs": {
                "insertions": 1,
                "deletions": 1
              }
            }
          }
        ]
      }
    ],
    "EthanWong2212": [
      {
        "date": "2020-10-02",
        "commitResults": [
          {
            "hash": "41ae61cfe1233e85efaff4047b9de0a46c53a0c9",
            "messageTitle": "tut random edit",
            "messageBody": "",
            "fileTypesAndContributionMap": {
              "docs": {
                "insertions": 2,
                "deletions": 0
              }
            }
          }
        ]
      }
    ],
    "mrwsy1": [
      {
        "date": "2020-10-02",
        "commitResults": [
          {
            "hash": "dbf969958be5c90fd4c22b24004b9b6efa4a5621",
            "messageTitle": "Test forking workflow",
            "messageBody": "",
            "fileTypesAndContributionMap": {
              "docs": {
                "insertions": 1,
                "deletions": 1
              }
            }
          }
        ]
      }
    ],
    "wamikamalik": [
      {
        "date": "2020-10-02",
        "commitResults": [
          {
            "hash": "0ee5c1149f912add14d02d51434ef31f6ef6c138",
            "messageTitle": "Update About us",
            "messageBody": "",
            "fileTypesAndContributionMap": {
              "docs": {
                "insertions": 7,
                "deletions": 1
              }
            }
          }
        ]
      }
    ]
  },
  "authorFileTypeContributionMap": {
    "Johnson-Yee": {
      "docs": 1,
      "functional-code": 0,
      "test-code": 0
    },
    "Lezn0": {
      "docs": 1,
      "functional-code": 0,
      "test-code": 0
    },
    "EthanWong2212": {
      "docs": 1,
      "functional-code": 0,
      "test-code": 0
    },
    "mrwsy1": {
      "docs": 1,
      "functional-code": 0,
      "test-code": 0
    },
    "wamikamalik": {
      "docs": 7,
      "functional-code": 0,
      "test-code": 0
    }
  },
  "authorContributionVariance": {
    "Johnson-Yee": 0.5555555,
    "Lezn0": 0.5555555,
    "EthanWong2212": 0.5555555,
    "mrwsy1": 0.5555555,
    "wamikamalik": 8.888888
  },
  "authorDisplayNameMap": {
    "Johnson-Yee": "CS2113T-F14-3 YEE ..NSON",
    "Lezn0": "CS2113T-F14-3 WU Y..UXIN",
    "EthanWong2212": "CS2113T-F14-3 WONG..CHIN",
    "mrwsy1": "CS2113T-F14-3 WANG..HUYI",
    "wamikamalik": "CS2113T-F14-3 WAMI..ALIK"
  }
}
